pyiec61850.libs/libiec61850-4dd27b28.so.1.5.2
pyiec61850/test_pyiec61850.py
pyiec61850/iec61850.py
pyiec61850/_iec61850.so
pyiec61850/__init__.py
pyiec61850-1.5.2a1.dist-info/METADATA
pyiec61850-1.5.2a1.dist-info/WHEEL
pyiec61850-1.5.2a1.dist-info/COPYING
pyiec61850-1.5.2a1.dist-info/RECORD
pyiec61850-1.5.2a1.dist-info/top_level.txt
