Metadata-Version: 2.1
Name: pyiec61850
Version: 1.5.2a1
Summary: Python bindings of https://github.com/mz-automation/libiec61850.
License-File: COPYING
